nuxt_payload/__init__.py
nuxt_payload/core.py
nuxt_payload-0.1.4.dist-info/licenses/AUTHORS.md
nuxt_payload-0.1.4.dist-info/licenses/LICENSE
nuxt_payload-0.1.4.dist-info/METADATA
nuxt_payload-0.1.4.dist-info/WHEEL
nuxt_payload-0.1.4.dist-info/top_level.txt
nuxt_payload-0.1.4.dist-info/RECORD
